django_satispaython/__init__.py
django_satispaython/_core.py
django_satispaython/admin.py
django_satispaython/api.py
django_satispaython/apps.py
django_satispaython/exceptions.py
django_satispaython/migrations/0001_initial.py
django_satispaython/migrations/__init__.py
django_satispaython/models.py
django_satispaython/templates/django_satispaython/satispay_button.html
django_satispaython/templatetags/__init__.py
django_satispaython/templatetags/django_satispaython.py
django_satispaython-0.1.4.dist-info/LICENSE
django_satispaython-0.1.4.dist-info/WHEEL
django_satispaython-0.1.4.dist-info/METADATA
django_satispaython-0.1.4.dist-info/RECORD
